credit_derivatives/__init__.py
credit_derivatives/_version.py
credit_derivatives-0.0.1.dist-info/LICENSE
credit_derivatives-0.0.1.dist-info/METADATA
credit_derivatives-0.0.1.dist-info/WHEEL
credit_derivatives-0.0.1.dist-info/top_level.txt
credit_derivatives-0.0.1.dist-info/RECORD
